doddle/__init__.py
doddle/__main__.py
doddle/benchmarking.py
doddle/boards.py
doddle/cli.py
doddle/controllers.py
doddle/engine.py
doddle/enums.py
doddle/exceptions.py
doddle/facade.py
doddle/factory.py
doddle/game.py
doddle/graph.py
doddle/guess.py
doddle/histogram.py
doddle/scoring.py
doddle/simul_solver.py
doddle/solver.py
doddle/tree.py
doddle/views.py
doddle/words.py
doddle/dictionaries/dictionary-answers-official.json
doddle/dictionaries/dictionary-answers.json
doddle/dictionaries/dictionary-full-official.json
doddle/dictionaries/dictionary-full.json
doddle-1.6.0.dist-info/LICENSE
doddle-1.6.0.dist-info/METADATA
doddle-1.6.0.dist-info/WHEEL
doddle-1.6.0.dist-info/entry_points.txt
doddle-1.6.0.dist-info/top_level.txt
doddle-1.6.0.dist-info/RECORD
