Metadata-Version: 2.1
Name: doddle
Version: 1.6.0
Summary: doddle: Make Wordle A Doddle
Home-page: https://github.com/CatchemAl/Doddle
Author: Alex Cross
Author-email: AlexJCross90@gmail.com
License: UNKNOWN
Project-URL: Bug Tracker, https://github.com/CatchemAl/Doddle/issues
Platform: UNKNOWN
Classifier: Programming Language :: Python
Classifier: Programming Language :: Python :: 3
Classifier: Programming Language :: Python :: 3 :: Only
Classifier: Programming Language :: Python :: 3.8
Classifier: Programming Language :: Python :: 3.9
Classifier: Programming Language :: Python :: 3.10
Classifier: License :: OSI Approved :: MIT License
Classifier: Operating System :: OS Independent
Requires-Python: >=3.8
License-File: LICENSE
Requires-Dist: numba
Requires-Dist: numpy
Requires-Dist: colorama
Requires-Dist: tqdm
Provides-Extra: decision
Requires-Dist: graphviz ; extra == 'decision'
Provides-Extra: dev
Requires-Dist: black ; extra == 'dev'
Requires-Dist: flake8 ; extra == 'dev'
Requires-Dist: isort ; extra == 'dev'
Requires-Dist: mypy ; extra == 'dev'
Requires-Dist: types-colorama ; extra == 'dev'
Requires-Dist: pytest-cov ; extra == 'dev'
Requires-Dist: tox ; extra == 'dev'
